Workbook

Sheet 1. Read me
A1: AI TCO / FinOps Calculator - how to use
A3: Purpose | B3: Model the annual run-rate cost of an AI use-case across model routing, cache-hit, fallback/retry, and supporting infra. Compare per-seat (M365 Copilot) vs per-token (Foundry) economics.
A4: Author | B4: Yuri Baijnath — CSU Cloud & AI Lead (South Africa), Microsoft
A5: Version | B5: 1.0 · 2026-06-03
A6: When to use | B6: Pre-pilot sizing (Gate 2), production go-live forecast (Gate 3), quarterly attestation re-forecast (Gate 4).
A7: Inputs (yellow cells) | B7: Edit only yellow cells. Sheets: 2. Pricing reference, 3. Inputs, 5. Scenarios.
A8: Results (green cells) | B8: Computed from inputs. Do not overwrite. Sheets: 4. Run-rate forecast, 6. Per-seat vs per-token.
A9: Pricing currency | B9: USD per 1,000 tokens (industry convention). Convert to ZAR at sheet 4 footer.
A10: Model routing | B10: gpt-4o (heavy reasoning), gpt-4o-mini (default), Phi-3 (fast/cheap fallback). Adjust mix on sheet 3.
A11: Cache-hit assumption | B11: Cached responses cost ~10% of un-cached (storage + lookup only). Default cache-hit 30%.
A12: Fallback / retry | B12: Fallback fires when primary model rejects (Content Safety / Prompt Shields / timeout). Retry fires on transient failure. Both add tokens.
A13: Per-seat trade-off | B13: M365 Copilot is per-user-per-month; Foundry agents are per-token. Sheet 6 surfaces the cross-over point.
A14: Cross-references | B14: Objection 1.3 (Copilot per-seat doesn't pencil); Objection 4.6 (cost overrun at scale); VBD D3 (FinOps for AI); WAF Cost Optimisation pillar.
A15: Disclaimer | B15: Pricing changes. Re-verify on https://azure.microsoft.com/en-us/pricing/ before any customer commit. All figures are planning estimates, not quotes.

Sheet 2. Pricing reference
A1: Pricing reference - edit yellow cells to match latest published Azure rates
A2: Item | B2: Unit | C2: USD / unit | D2: Notes
A3: gpt-4o input | B3: 1k tokens | C3: 0.0025 | D3: Heavy reasoning, vision; check Azure pricing for current
A4: gpt-4o output | B4: 1k tokens | C4: 0.01
A5: gpt-4o-mini input | B5: 1k tokens | C5: 0.00015 | D5: Default workhorse
A6: gpt-4o-mini output | B6: 1k tokens | C6: 0.0006
A7: Phi-3-medium input | B7: 1k tokens | C7: 5e-05 | D7: Fallback / fast lane (planning estimate)
A8: Phi-3-medium output | B8: 1k tokens | C8: 0.0002
A9: text-embedding-3-large | B9: 1k tokens | C9: 0.00013 | D9: Vector index ingestion
A10: Cached output (uplift factor) | B10: ratio | C10: 0.1 | D10: Cached call cost as % of un-cached - tune per workload
A11: AI Search S1 | B11: instance / month | C11: 250 | D11: Vector index host (planning estimate)
A12: Blob storage (hot) | B12: GB / month | C12: 0.02 | D12: Document corpus + prompt logs
A13: Content Safety call | B13: 1k calls | C13: 0.75 | D13: Both input + output filter
A14: Defender for Cloud AI | B14: resource / month | C14: 7 | D14: Per protected resource (estimate)
A15: Purview AI Hub | B15: user / month | C15: 4 | D15: Per monitored user (estimate)
A16: Log Analytics ingestion | B16: GB | C16: 2.3 | D16: Monitoring + audit log
A17: M365 Copilot license | B17: user / month | C17: 30 | D17: Per-seat baseline (USD list)

Sheet 3. Inputs
A1: Inputs - edit yellow cells. One use-case per workbook (copy sheet to model more).
A2: Parameter | B2: Value | C2: Unit | D2: Notes
A3: Use-case name | B3: Claims triage agent (sample) | D3: Replace with your use-case
A4: Users | B4: 500 | C4: active users | D4: Concurrent / licensed seat count
A5: Queries per user per day | B5: 12 | C5: queries | D5: Empirical; instrument and refine
A6: Working days per month | B6: 22 | C6: days
A7: Avg input tokens per query | B7: 1500 | C7: tokens | D7: Includes system + retrieved context
A8: Avg output tokens per query | B8: 400 | C8: tokens
A9: % routed to gpt-4o | B9: 0.2 | C9: share 0-1 | D9: Heavy reasoning calls
A10: % routed to gpt-4o-mini | B10: 0.65 | C10: share 0-1 | D10: Default workhorse
A11: % routed to Phi-3 | B11: 0.15 | C11: share 0-1 | D11: Fast/cheap fallback
A12: Cache-hit rate | B12: 0.3 | C12: share 0-1 | D12: Higher for FAQ / repeated intents
A13: Fallback rate (CS/Prompt-Shield reject -> re-route) | B13: 0.05 | C13: share 0-1 | D13: Adds full second call at fallback model
A14: Retry rate (transient) | B14: 0.02 | C14: share 0-1 | D14: Adds full second call at same model
A15: Vector index size | B15: 50 | C15: GB | D15: Document corpus indexed
A16: Embeddings refresh per month | B16: 5 | C16: GB | D16: Delta re-indexed monthly
A17: Blob storage (logs + corpus) | B17: 200 | C17: GB
A18: Content Safety enabled | B18: 1 | C18: 1=yes 0=no
A19: Defender for Cloud AI resources | B19: 6 | C19: resources | D19: Foundry endpoint, AI Search, KV, etc.
A20: Purview AI Hub monitored users | B20: 500 | C20: users | D20: Usually = active users
A21: Log Analytics ingestion / month | B21: 20 | C21: GB
A22: M365 Copilot per-seat sizing (for comparison) | B22: 500 | C22: seats | D22: Used on sheet 6
A23: USD->ZAR FX | B23: 18.5 | C23: ZAR per USD | D23: Update at fiscal start

Sheet 4. Run-rate forecast
A1: Run-rate forecast - per-token Foundry path (per-seat path on sheet 6)
A2: Line item | B2: Monthly USD | C2: Annual USD | D2: Annual ZAR | E2: How computed
A3: gpt-4o (heavy reasoning) | B3: =((('3. Inputs'!$B$4*'3. Inputs'!$B$5*'3. Inputs'!$B$6)*((1-'3. Inputs'!$B$12)+('3. Inputs'!$B$12*'2. Pricing reference'!$C$10)))*'3. Inputs'!$B$9*('3. Inputs'!$B$7/1000*'2. Pricing reference'!$C$3+'3. Inputs'!$B$8/1000*'2. Pricing reference'!$C$4)*(1+'3. Inputs'!$B$14+'3. Inputs'!$B$13)) | C3: =B3*12 | D3: =C3*'3. Inputs'!$B$23 | E3: % mix * (input+output tokens * price) * (1+retry+fallback), cache-adjusted
A4: gpt-4o-mini (default) | B4: =((('3. Inputs'!$B$4*'3. Inputs'!$B$5*'3. Inputs'!$B$6)*((1-'3. Inputs'!$B$12)+('3. Inputs'!$B$12*'2. Pricing reference'!$C$10)))*'3. Inputs'!$B$10*('3. Inputs'!$B$7/1000*'2. Pricing reference'!$C$5+'3. Inputs'!$B$8/1000*'2. Pricing reference'!$C$6)*(1+'3. Inputs'!$B$14+'3. Inputs'!$B$13)) | C4: =B4*12 | D4: =C4*'3. Inputs'!$B$23 | E4: as above
A5: Phi-3 (fast lane) | B5: =((('3. Inputs'!$B$4*'3. Inputs'!$B$5*'3. Inputs'!$B$6)*((1-'3. Inputs'!$B$12)+('3. Inputs'!$B$12*'2. Pricing reference'!$C$10)))*'3. Inputs'!$B$11*('3. Inputs'!$B$7/1000*'2. Pricing reference'!$C$7+'3. Inputs'!$B$8/1000*'2. Pricing reference'!$C$8)*(1+'3. Inputs'!$B$14+'3. Inputs'!$B$13)) | C5: =B5*12 | D5: =C5*'3. Inputs'!$B$23 | E5: as above
A6: Embeddings refresh | B6: =('3. Inputs'!$B$16*1024*1024/4*'2. Pricing reference'!$C$9/1000) | C6: =B6*12 | D6: =C6*'3. Inputs'!$B$23 | E6: Embedding tokens per GB delta * price
A7: AI Search (vector index host) | B7: ='2. Pricing reference'!$C$11 | C7: =B7*12 | D7: =C7*'3. Inputs'!$B$23 | E7: S1 instance
A8: Blob storage (logs + corpus) | B8: =('3. Inputs'!$B$17*'2. Pricing reference'!$C$12) | C8: =B8*12 | D8: =C8*'3. Inputs'!$B$23 | E8: GB * price
A9: Content Safety | B9: =(IF('3. Inputs'!$B$18=1,('3. Inputs'!$B$4*'3. Inputs'!$B$5*'3. Inputs'!$B$6)*2/1000*'2. Pricing reference'!$C$13,0)) | C9: =B9*12 | D9: =C9*'3. Inputs'!$B$23 | E9: 2 calls per query (input + output filter)
A10: Defender for Cloud AI | B10: =('3. Inputs'!$B$19*'2. Pricing reference'!$C$14) | C10: =B10*12 | D10: =C10*'3. Inputs'!$B$23 | E10: Resources * price
A11: Purview AI Hub | B11: =('3. Inputs'!$B$20*'2. Pricing reference'!$C$15) | C11: =B11*12 | D11: =C11*'3. Inputs'!$B$23 | E11: Monitored users * price
A12: Log Analytics | B12: =('3. Inputs'!$B$21*'2. Pricing reference'!$C$16) | C12: =B12*12 | D12: =C12*'3. Inputs'!$B$23 | E12: Ingestion GB * price
A13: TOTAL (per-token path) | B13: =SUM(B3:B12) | C13: =SUM(C3:C12) | D13: =SUM(D3:D12) | E13: Sum of above
A15: Cost per query (USD) | B15: =B13/('3. Inputs'!$B$4*'3. Inputs'!$B$5*'3. Inputs'!$B$6)
A16: Cost per user / month (USD) | B16: =B13/'3. Inputs'!$B$4
A17: Cost per user / month (ZAR) | B17: =B16*'3. Inputs'!$B$23

Sheet 5. Scenarios
A1: Three pre-loaded scenarios - copy column into sheet 3 to re-cost
A2: Parameter | B2: Low intensity | C2: Mid intensity (default) | D2: High intensity | E2: Unit | F2: Notes
A3: Users | B3: 200 | C3: 500 | D3: 2000 | E3: users | F3: Concurrent licensed users
A4: Queries per user per day | B4: 5 | C4: 12 | D4: 30 | E4: queries | F4: Low = ad-hoc; mid = daily; high = power
A5: Working days per month | B5: 22 | C5: 22 | D5: 22 | E5: days
A6: Avg input tokens | B6: 800 | C6: 1500 | D6: 3000 | E6: tokens | F6: Heavier RAG -> larger context
A7: Avg output tokens | B7: 200 | C7: 400 | D7: 800 | E7: tokens
A8: % gpt-4o | B8: 0.05 | C8: 0.2 | D8: 0.4 | E8: share | F8: More reasoning -> more 4o
A9: % gpt-4o-mini | B9: 0.7 | C9: 0.65 | D9: 0.5 | E9: share
A10: % Phi-3 | B10: 0.25 | C10: 0.15 | D10: 0.1 | E10: share
A11: Cache-hit rate | B11: 0.45 | C11: 0.3 | D11: 0.15 | E11: share | F11: Lower for varied workloads
A12: Fallback rate | B12: 0.03 | C12: 0.05 | D12: 0.08 | E12: share
A13: Retry rate | B13: 0.01 | C13: 0.02 | D13: 0.04 | E13: share
A14: Vector index (GB) | B14: 10 | C14: 50 | D14: 250 | E14: GB
A15: Blob storage (GB) | B15: 50 | C15: 200 | D15: 1000 | E15: GB
A16: Defender resources | B16: 4 | C16: 6 | D16: 12 | E16: resources
A17: Log Analytics (GB/mo) | B17: 5 | C17: 20 | D17: 100 | E17: GB
A18: Indicative annual USD (est.) | B18: see sheet 4 | C18: see sheet 4 | D18: see sheet 4 | E18: USD | F18: Re-run sheet 4 with these inputs to compute

Sheet 6. Per-seat vs per-token
A1: Per-seat (M365 Copilot) vs per-token (Foundry) trade-off
A2: Path | B2: Monthly USD | C2: Annual USD | D2: Annual ZAR | E2: How computed
A3: M365 Copilot per-seat | B3: ='3. Inputs'!$B$22*'2. Pricing reference'!$C$17 | C3: =B3*12 | D3: =C3*'3. Inputs'!$B$23 | E3: Seats * per-user-per-month
A4: Foundry agent per-token (from sheet 4) | B4: ='4. Run-rate forecast'!B13 | C4: =B4*12 | D4: =C4*'3. Inputs'!$B$23 | E4: Total of sheet 4
A5: Delta (per-seat - per-token), annual USD | C5: =C3-C4 | D5: =D3-D4
A7: Reading the trade-off:
A8: - If Foundry < per-seat: per-token path is cheaper at current usage; revisit at adoption inflection.
A9: - If per-seat < Foundry: M365 Copilot is the right entry point; expand to Foundry agents for heavy reasoning only.
A10: - Crossover usually lies between 10-25 q/u/d depending on input-token size and model mix.
A11: Important: M365 Copilot bundles M365 surface integration value not captured in token economics; assess qualitatively.
A12: Cross-references: Objection 1.3 (per-seat doesn't pencil), Objection 4.6 (cost overrun), VBD D3 (FinOps for AI).

Sheet 7. WAF binding
A1: Well-Architected Framework - Cost Optimisation pillar binding
A2: WAF Cost Optimisation principle | B2: How this calculator binds | C2: Owner
A3: Choose the right resources | B3: Model routing tab (3. Inputs rows 9-11) defaults to mini; routes 4o only for heavy reasoning | C3: Engineering lead
A4: Set up budgets and maintain cost constraints | B4: Annual ZAR figure (sheet 4) feeds Azure budget alert; recommended alert at 75/90/100% | C4: FinOps lead
A5: Dynamically allocate and de-allocate | B5: Cache-hit rate (3. Inputs row 12) drives semantic caching choice; fallback rate row 13 sizes Phi-3 capacity | C5: Engineering lead
A6: Optimise rates | B6: Pricing reference (sheet 2) editable; verify against Reservation / Commitment discounts before commit | C6: Procurement lead
A7: Monitor and report cost | B7: Log Analytics line on sheet 4 funds the monitoring estate; combine with Cost Mgmt + AI Studio metrics | C7: Operations lead
A8: Refine over time | B8: Quarterly attestation should re-run this workbook with refreshed inputs; drift > 15% triggers re-baseline | C8: FinOps lead + CSA
